rospec/__init__.py
rospec/cli.py
rospec/errors.py
rospec/language/__init__.py
rospec/language/frontend.py
rospec/language/grammar.lark
rospec/language/nodes.py
rospec/language/ttypes.py
rospec/language/utils.py
rospec/types_database/__init__.py
rospec/types_database/ttypes_loader.py
rospec/types_database/ttypes/ardrone_autonomy.rospec
rospec/types_database/ttypes/dynamic_reconfigure.rospec
rospec/types_database/ttypes/geometry_msgs.rospec
rospec/types_database/ttypes/hector_nav_msgs.rospec
rospec/types_database/ttypes/move_base_msgs.rospec
rospec/types_database/ttypes/nav2_msgs.rospec
rospec/types_database/ttypes/nav_msgs.rospec
rospec/types_database/ttypes/rosgraph_msgs.rospec
rospec/types_database/ttypes/sensor_msgs.rospec
rospec/types_database/ttypes/std_msgs.rospec
rospec/types_database/ttypes/std_srvs.rospec
rospec/types_database/ttypes/tf2_msgs.rospec
rospec/types_database/ttypes/turtlesim.rospec
rospec/types_database/ttypes/visualization_msgs.rospec
rospec/verification/__init__.py
rospec/verification/context.py
rospec/verification/definition_formation.py
rospec/verification/expression_formation.py
rospec/verification/interpreter.py
rospec/verification/statement_formation.py
rospec/verification/substitution.py
rospec/verification/subtyping.py
rospec/verification/type_formation.py
rospec/verification/utils.py
rospec-0.1.0.dist-info/METADATA
rospec-0.1.0.dist-info/WHEEL
rospec-0.1.0.dist-info/entry_points.txt
rospec-0.1.0.dist-info/licenses/LICENSE
rospec-0.1.0.dist-info/RECORD
