Metadata-Version: 2.4
Name: rospec
Version: 0.1.0
Summary: Specification and verification of ROS-based robot software
Project-URL: Homepage, https://github.com/pcanelas/rospec
Project-URL: Repository, https://github.com/pcanelas/rospec
Project-URL: Issues, https://github.com/pcanelas/rospec/issues
Author: Bradley Schmerl, Alcides Fonseca, Christopher S. Timperley
Author-email: Paulo Canelas <pasantos@andrew.cmu.edu>
License: Apache-2.0
License-File: LICENSE
Keywords: robotics,ros,specification,verification
Classifier: Development Status :: 3 - Alpha
Classifier: Intended Audience :: Developers
Classifier: License :: OSI Approved :: Apache Software License
Classifier: Programming Language :: Python :: 3
Classifier: Programming Language :: Python :: 3.9
Classifier: Programming Language :: Python :: 3.10
Classifier: Programming Language :: Python :: 3.11
Classifier: Programming Language :: Python :: 3.12
Classifier: Topic :: Scientific/Engineering :: Artificial Intelligence
Classifier: Topic :: Software Development :: Libraries :: Python Modules
Requires-Python: >=3.9
Requires-Dist: lark==1.2.2
Requires-Dist: loguru==0.7.3
Requires-Dist: pytest-xdist>=3.8.0
Requires-Dist: rich==14.0.0
Provides-Extra: dev
Requires-Dist: mypy==1.15.0; extra == 'dev'
Requires-Dist: pep8-naming==0.14.1; extra == 'dev'
Requires-Dist: pre-commit>=4.2.0; extra == 'dev'
Requires-Dist: ptpython==3.0.29; extra == 'dev'
Requires-Dist: pytest==8.3.5; extra == 'dev'
Requires-Dist: ruff==0.11.10; extra == 'dev'
Requires-Dist: tox==4.25.0; extra == 'dev'
Requires-Dist: twine==6.1.0; extra == 'dev'
Requires-Dist: types-setuptools==78.1.0.20250329; extra == 'dev'
Requires-Dist: yapf==0.43.0; extra == 'dev'
